LICENSE
dispmanx/__init__.py
dispmanx/bcm_host.py
dispmanx/dispmanx.py
dispmanx/exceptions.py
dispmanx-0.1.0.dist-info/LICENSE
dispmanx-0.1.0.dist-info/WHEEL
dispmanx-0.1.0.dist-info/METADATA
dispmanx-0.1.0.dist-info/RECORD
