Metadata-Version: 2.1
Name: dispmanx
Version: 0.1.0
Summary: Libraty providing a buffer interface to your Raspberry Pi's GPU layer. Usable with pygame, PIL and other graphics libraries.
Home-page: https://github.com/dtcooper/python-dispmanx
License: MIT
Author: David Cooper
Author-email: david@dtcooper.com
Requires-Python: >=3.9,<4.0
Classifier: Development Status :: 3 - Alpha
Classifier: License :: OSI Approved :: MIT License
Classifier: Programming Language :: Python :: 3
Classifier: Programming Language :: Python :: 3.10
Classifier: Programming Language :: Python :: 3.9
Classifier: Topic :: Multimedia :: Graphics
Classifier: Topic :: Software Development :: Libraries :: Python Modules
Classifier: Topic :: Software Development :: Libraries :: pygame
Provides-Extra: numpy
Requires-Dist: numpy (<2); extra == "numpy"
Project-URL: Repository, https://github.com/dtcooper/python-dispmanx
